AUTHORS
LICENSE
MANIFEST.in
README
aff4_errors.h
class.cpp
class.h
class_parser.py
error.cpp
generate_bindings.py
lexer.py
misc.h
pyproject.toml
pytsk3.cpp
pytsk3.h
run_tests.py
setup.cfg
setup.py
tsk3.cpp
tsk3.h
dpkg/changelog
dpkg/compat
dpkg/control
dpkg/copyright
dpkg/python-pytsk3.docs
dpkg/python3-pytsk3.docs
dpkg/rules
dpkg/source/format
dpkg/source/options
patches/sleuthkit-4.14.0-configure.ac
pytsk3.egg-info/PKG-INFO
pytsk3.egg-info/SOURCES.txt
pytsk3.egg-info/dependency_links.txt
pytsk3.egg-info/top_level.txt
sleuthkit/.git
sleuthkit/.gitattributes
sleuthkit/.gitignore
sleuthkit/.travis.yml
sleuthkit/API-CHANGES.txt
sleuthkit/ChangeLog.txt
sleuthkit/INSTALL.txt
sleuthkit/Makefile
sleuthkit/Makefile.am
sleuthkit/Makefile.in
sleuthkit/NEWS.txt
sleuthkit/README.md
sleuthkit/README_win32.txt
sleuthkit/aclocal.m4
sleuthkit/appveyor.yml
sleuthkit/bootstrap
sleuthkit/config.log
sleuthkit/config.status
sleuthkit/configure
sleuthkit/configure.ac
sleuthkit/libtool
sleuthkit/ruleset.xml
sleuthkit/travis_install_libs.sh
sleuthkit/.github/workflows/build-unix.yml
sleuthkit/case-uco/java/Makefile.am
sleuthkit/case-uco/java/README.md
sleuthkit/case-uco/java/build.xml
sleuthkit/case-uco/java/ivy.xml
sleuthkit/case-uco/java/ivysettings.xml
sleuthkit/case-uco/java/manifest.mf
sleuthkit/case-uco/java/nbproject/build-impl.xml
sleuthkit/case-uco/java/nbproject/project.properties
sleuthkit/case-uco/java/nbproject/project.xml
sleuthkit/case-uco/java/src/org/sleuthkit/caseuco/Account.java
sleuthkit/case-uco/java/src/org/sleuthkit/caseuco/AccountAuthentication.java
sleuthkit/case-uco/java/src/org/sleuthkit/caseuco/Action.java
sleuthkit/case-uco/java/src/org/sleuthkit/caseuco/ActionArgument.java
sleuthkit/case-uco/java/src/org/sleuthkit/caseuco/Annotation.java
sleuthkit/case-uco/java/src/org/sleuthkit/caseuco/Application.java
sleuthkit/case-uco/java/src/org/sleuthkit/caseuco/ApplicationAccount.java
sleuthkit/case-uco/java/src/org/sleuthkit/caseuco/Assertion.java
sleuthkit/case-uco/java/src/org/sleuthkit/caseuco/Attachment.java
