Metadata-Version: 2.4
Name: pytsk3
Version: 20250729
Summary: Python bindings for the SleuthKit
Home-page: https://github.com/py4n6/pytsk
Author: Michael Cohen
Author-email: scudette@gmail.com
Maintainer: Joachim Metz
Maintainer-email: joachim.metz@gmail.com
License: Apache License, Version 2.0
Classifier: Development Status :: 3 - Alpha
Classifier: Programming Language :: Python
Requires-Python: >=3.8
